sheet2dict/__init__.py
sheet2dict/main.py
tests/__init__.py
tests/conftest.py
tests/test_1_xlsx.py
tests/test_2_csv.py
tests/test_3_xlsx.py
tests/x-custom_tests.py
sheet2dict-0.1.5.dist-info/LICENSE
sheet2dict-0.1.5.dist-info/METADATA
sheet2dict-0.1.5.dist-info/WHEEL
sheet2dict-0.1.5.dist-info/top_level.txt
sheet2dict-0.1.5.dist-info/RECORD
