Metadata-Version: 2.1
Name: sheet2dict
Version: 0.1.5
Summary: Simple XLSX and CSV to dictionary converter
Author-email: Tomas Pytel <pytlicek@gmail.com>
Project-URL: Homepage, https://github.com/Pytlicek/sheet2dict
Classifier: Programming Language :: Python :: 3
Classifier: License :: OSI Approved :: MIT License
Classifier: Operating System :: OS Independent
Requires-Python: >=3.6
License-File: LICENSE
Requires-Dist: openpyxl
